fishyer_helper/__init__.py
fishyer_helper/log_util.py
fishyer_helper/math_util.py
fishyer_helper/redis_util.py
fishyer_test/__init__.py
fishyer_test/log_util.py
fishyer_test/math_util.py
fishyer_helper-0.0.3.dist-info/METADATA
fishyer_helper-0.0.3.dist-info/WHEEL
fishyer_helper-0.0.3.dist-info/top_level.txt
fishyer_helper-0.0.3.dist-info/RECORD
