Metadata-Version: 2.1
Name: fishyer-helper
Version: 0.0.3
Summary: My Python Util Package
Home-page: https://github.com/fishyer/python-util
Author: fishyer
Author-email: yutianran66@gamil.com
Classifier: Programming Language :: Python :: 3
Classifier: License :: OSI Approved :: MIT License
